{
  "/_error": "pages/_error.js",
  "/_document": "pages/_document.js",
  "/dashboard": "pages/dashboard.html",
  "/about": "pages/about.html",
  "/": "pages/index.html",
  "/login": "pages/login.html",
  "/minerals": "pages/minerals.html",
  "/profile": "pages/profile.html",
  "/signup": "pages/signup.html",
  "/agriculture": "pages/agriculture.html",
  "/minerals_new": "pages/minerals_new.html",
  "/diesel-ulp": "pages/diesel-ulp.html",
  "/refineries": "pages/refineries.html",
  "/contact": "pages/contact.html",
  "/store": "pages/store.html",
  "/stonehouse-estates": "pages/stonehouse-estates.html",
  "/_app": "pages/_app.js",
  "/404": "pages/404.html"
}